dplus/Amplitudes.py
dplus/Backend.py
dplus/CalculationInput.py
dplus/CalculationResult.py
dplus/CalculationRunner.py
dplus/DataModels.py
dplus/FileReaders.py
dplus/FitRunner.py
dplus/PDBReaderLib.dll
dplus/PyCeresOptimizer.py
dplus/Residuals.py
dplus/Signal.py
dplus/State.py
dplus/__init__.py
dplus/cudart64_110.dll
dplus/curand64_10.dll
dplus/g_r.py
dplus/lua51-backend.dll
dplus/metadata.py
dplus/scipy_fit.py
dplus/wrappers.cp310-win_amd64.pyd
dplus/xplusbackend.dll
dplus_api-4.6.0.dist-info/LICENSE.txt
dplus_api-4.6.0.dist-info/METADATA
dplus_api-4.6.0.dist-info/WHEEL
dplus_api-4.6.0.dist-info/top_level.txt
dplus_api-4.6.0.dist-info/RECORD
