Metadata-Version: 2.1
Name: dplus-api
Version: 4.6.0
Summary: Call the DPlus Calculation Backend
Home-page: https://scholars.huji.ac.il/uriraviv
Author: Devora Witty
Author-email: devorawitty@chelem.co.il
License: D+ Software
Platform: UNKNOWN
Classifier: Development Status :: 4 - Beta
Classifier: Environment :: Console
Classifier: Intended Audience :: Science/Research
Classifier: License :: Other/Proprietary License
Classifier: Operating System :: OS Independent
Classifier: Programming Language :: Python
Classifier: Programming Language :: Python :: 3.8
Classifier: Programming Language :: Python :: 3.9
Classifier: Programming Language :: Python :: 3.10
Classifier: Topic :: Scientific/Engineering :: Chemistry
License-File: LICENSE.txt
Requires-Dist: numpy (<=1.24,>=1.23)
Requires-Dist: psutil (>=5.6.3)
Requires-Dist: requests (>=2.10.0)
Requires-Dist: dplus-ceres (>=0.4.0)
